sundew/__init__.py
sundew/__main__.py
sundew/config.py
sundew/graph.py
sundew/main.py
sundew/side_effects.py
sundew/test_runner.py
sundew/test_writer.py
sundew/types.py
sundew/utils.py
sundew-0.2.0.dist-info/LICENSE.txt
sundew-0.2.0.dist-info/METADATA
sundew-0.2.0.dist-info/WHEEL
sundew-0.2.0.dist-info/entry_points.txt
sundew-0.2.0.dist-info/RECORD
