Metadata-Version: 2.1
Name: sundew
Version: 0.2.0
Summary: 
Home-page: https://github.com/devenjarvis/sundew
License: MIT
Keywords: testing
Author: devenjarvis
Author-email: devenjarvis@gmail.com
Requires-Python: >=3.9,<4.0
Classifier: License :: OSI Approved :: MIT License
Classifier: Programming Language :: Python :: 3
Classifier: Programming Language :: Python :: 3.9
Classifier: Programming Language :: Python :: 3.10
Classifier: Programming Language :: Python :: 3.11
Classifier: Topic :: Software Development :: Testing
Requires-Dist: black
Requires-Dist: cachetools
Requires-Dist: httpx (>=0.23.3,<0.24.0)
Requires-Dist: poetry (>=1.4.0,<2.0.0)
Requires-Dist: pydantic (>=1.10.2,<2.0.0)
Requires-Dist: typer[all] (>=0.7.0,<0.8.0)
Project-URL: Documentation, https://devenjarvis.github.io/sundew/#/
Project-URL: Repository, https://github.com/devenjarvis/sundew
